{
    "source": "tmdb",
    "tmdb_id": 255979,
    "cinear_id": 1389,
    "slug": "balnearios",
    "title": "Balnearios",
    "original_title": "Balnearios",
    "overview": "Un álbum de historias extrañas y humorísticas sobre pequeños lugares dedicados exclusivamente a la molicie, vacíos en invierno, abarrotados en verano: los balnearios. Ciudades bajo el agua, hoteles de lujo, sirenas, animales marinos, castillos de arena, gente que rinde culto al agua pidiendo salud.",
    "runtime": 82,
    "release_date": "2002-04-23",
    "year": 2002,
    "tagline": "",
    "genres": [
        {
            "id": 99,
            "name": "Documental"
        }
    ],
    "countries": [
        "Argentina"
    ],
    "spoken_languages": [
        "Español"
    ],
    "poster_url": "/storage/posters/balnearios-3d68d5c4.jpg",
    "backdrop_url": "/storage/backdrops/balnearios-ec82f555.jpg",
    "trailer": null,
    "gallery_urls": [
        "/storage/posters/balnearios-3d68d5c4.jpg",
        "/storage/gallery/gallery-2-eaaae18d.jpg",
        "/storage/gallery/gallery-3-56ab3d5f.jpg"
    ],
    "cast": [
        {
            "id": 2265483,
            "name": "José Palomino",
            "character": "Self (voice)",
            "order": 0,
            "image_url": "/storage/people/jose-palomino-efe10f0e.jpg"
        },
        {
            "id": 66959,
            "name": "Verónica Llinás",
            "character": "Self (voice)",
            "order": 1,
            "image_url": "/storage/people/veronica-llinas-bcaa0790.jpg"
        },
        {
            "id": 1957315,
            "name": "Daniel Natanson",
            "character": "Self (voice)",
            "order": 2,
            "image_url": null
        },
        {
            "id": 2128004,
            "name": "Mario Mactas",
            "character": "Self (voice)",
            "order": 3,
            "image_url": null
        },
        {
            "id": 2609916,
            "name": "Eduardo Gamba",
            "character": "Mr. G.",
            "order": 4,
            "image_url": null
        },
        {
            "id": 555975,
            "name": "Nicolás Goldbart",
            "character": "Young G.",
            "order": 5,
            "image_url": "/storage/people/nicolas-goldbart-d850215c.jpg"
        },
        {
            "id": 935388,
            "name": "Rafael Filippelli",
            "character": "Lawyer",
            "order": 6,
            "image_url": "/storage/people/rafael-filippelli-f11607cb.jpg"
        },
        {
            "id": 2439028,
            "name": "Ulises de la Orden",
            "character": "Uruguayan",
            "order": 7,
            "image_url": "/storage/people/ulises-de-la-orden-75439f81.jpg"
        },
        {
            "id": 1817493,
            "name": "Astrid Lund Petersen",
            "character": "Singer",
            "order": 8,
            "image_url": null
        },
        {
            "id": 2609921,
            "name": "Sergio Saad",
            "character": "Sailor",
            "order": 9,
            "image_url": null
        },
        {
            "id": 2609926,
            "name": "Eduardo 'Fatiga' Serrano",
            "character": "Lifeguard",
            "order": 10,
            "image_url": null
        },
        {
            "id": 2276357,
            "name": "Wenceslao Bonelli",
            "character": "Champion",
            "order": 11,
            "image_url": null
        },
        {
            "id": 2609930,
            "name": "Luis Pierucci",
            "character": "Guide",
            "order": 12,
            "image_url": null
        },
        {
            "id": 2609931,
            "name": "Ricardo Mannero",
            "character": "Aquanaut",
            "order": 13,
            "image_url": null
        },
        {
            "id": 2609932,
            "name": "Liliana Cuomo",
            "character": "Mermaid",
            "order": 14,
            "image_url": null
        },
        {
            "id": 2609935,
            "name": "Roberto Edgar Ojeda",
            "character": "Guitarist #1",
            "order": 15,
            "image_url": null
        },
        {
            "id": 2609936,
            "name": "Osvaldo Lucero",
            "character": "Guitarist #2",
            "order": 16,
            "image_url": null
        },
        {
            "id": 2609938,
            "name": "Eugenia Varas",
            "character": "Swimmer",
            "order": 17,
            "image_url": null
        },
        {
            "id": 1293509,
            "name": "Mariano Llinás",
            "character": "Model",
            "order": 18,
            "image_url": "/storage/people/mariano-llinas-e3570d76.jpg"
        },
        {
            "id": 2609907,
            "name": "Alejandro Zucco",
            "character": "Son",
            "order": 19,
            "image_url": null
        }
    ],
    "crew": [
        {
            "id": 1293509,
            "name": "Mariano Llinás",
            "department": "Directing",
            "job": "Director",
            "image_url": "/storage/people/mariano-llinas-e3570d76.jpg"
        },
        {
            "id": 1791449,
            "name": "Agustín Rolandelli",
            "department": "Editing",
            "job": "Editor",
            "image_url": null
        },
        {
            "id": 555975,
            "name": "Nicolás Goldbart",
            "department": "Editing",
            "job": "Editor",
            "image_url": "/storage/people/nicolas-goldbart-d850215c.jpg"
        },
        {
            "id": 68145,
            "name": "Lucio Bonelli",
            "department": "Camera",
            "job": "Director of Photography",
            "image_url": "/storage/people/lucio-bonelli-154ae367.jpg"
        },
        {
            "id": 1293509,
            "name": "Mariano Llinás",
            "department": "Writing",
            "job": "Writer",
            "image_url": "/storage/people/mariano-llinas-e3570d76.jpg"
        },
        {
            "id": 1509683,
            "name": "Alejandro Israel",
            "department": "Production",
            "job": "Production Manager",
            "image_url": "/storage/people/alejandro-israel-26cacdaa.jpg"
        },
        {
            "id": 1587464,
            "name": "Gabriel Chwojnik",
            "department": "Sound",
            "job": "Original Music Composer",
            "image_url": "/storage/people/gabriel-chwojnik-35051c51.jpg"
        },
        {
            "id": 2609902,
            "name": "Manuela Willimburgh",
            "department": "Production",
            "job": "Executive Producer",
            "image_url": null
        },
        {
            "id": 1509683,
            "name": "Alejandro Israel",
            "department": "Production",
            "job": "Production Director",
            "image_url": "/storage/people/alejandro-israel-26cacdaa.jpg"
        },
        {
            "id": 1618439,
            "name": "Federico Esquerro",
            "department": "Sound",
            "job": "Sound",
            "image_url": null
        },
        {
            "id": 2062853,
            "name": "Fernando Ribero",
            "department": "Sound",
            "job": "Sound Recordist",
            "image_url": null
        },
        {
            "id": 2307443,
            "name": "Rufino Basavilbaso",
            "department": "Sound",
            "job": "Sound Recordist",
            "image_url": null
        },
        {
            "id": 2062851,
            "name": "Ana Mouriño",
            "department": "Sound",
            "job": "Sound Recordist",
            "image_url": null
        },
        {
            "id": 1467069,
            "name": "Guillermo Picco",
            "department": "Sound",
            "job": "Sound Recordist",
            "image_url": null
        },
        {
            "id": 1817498,
            "name": "Martín Mohadeb",
            "department": "Camera",
            "job": "Additional Director of Photography",
            "image_url": null
        },
        {
            "id": 2609905,
            "name": "Juan Pablo Cambariere",
            "department": "Art",
            "job": "Graphic Designer",
            "image_url": null
        },
        {
            "id": 2609907,
            "name": "Alejandro Zucco",
            "department": "Production",
            "job": "Production Coordinator",
            "image_url": null
        },
        {
            "id": 1706305,
            "name": "Agustín Mendilaharzu",
            "department": "Production",
            "job": "Researcher",
            "image_url": "/storage/people/agustin-mendilaharzu-ffd96724.jpg"
        }
    ],
    "raw": {
        "adult": false,
        "backdrop_path": "/l20Ync88qQEldfGMnoEnl1UscpB.jpg",
        "belongs_to_collection": null,
        "budget": 0,
        "genres": [
            {
                "id": 99,
                "name": "Documental"
            }
        ],
        "homepage": "",
        "id": 255979,
        "imdb_id": "tt0319031",
        "origin_country": [
            "AR"
        ],
        "original_language": "es",
        "original_title": "Balnearios",
        "overview": "Un álbum de historias extrañas y humorísticas sobre pequeños lugares dedicados exclusivamente a la molicie, vacíos en invierno, abarrotados en verano: los balnearios. Ciudades bajo el agua, hoteles de lujo, sirenas, animales marinos, castillos de arena, gente que rinde culto al agua pidiendo salud.",
        "popularity": 0.9937,
        "poster_path": "/jqHoLGPaYJou37YZXy0CytikU2i.jpg",
        "production_companies": [
            {
                "id": 20124,
                "logo_path": "/uyKNacxTuJItGNZoqMzPtKtZBLn.png",
                "name": "El Pampero Cine",
                "origin_country": "AR"
            }
        ],
        "production_countries": [
            {
                "iso_3166_1": "AR",
                "name": "Argentina"
            }
        ],
        "release_date": "2002-04-23",
        "revenue": 0,
        "runtime": 82,
        "spoken_languages": [
            {
                "english_name": "Spanish",
                "iso_639_1": "es",
                "name": "Español"
            }
        ],
        "status": "Released",
        "tagline": "",
        "title": "Balnearios",
        "video": false,
        "vote_average": 7,
        "vote_count": 13,
        "credits": {
            "cast": [
                {
                    "adult": false,
                    "gender": 0,
                    "id": 2265483,
                    "known_for_department": "Acting",
                    "name": "José Palomino",
                    "original_name": "José Palomino",
                    "popularity": 0.1177,
                    "profile_path": "/3TTNs97sLq79msl0tPCoSYMYbbh.jpg",
                    "cast_id": 16,
                    "character": "Self (voice)",
                    "credit_id": "5e9efa77eec5b5001a41b908",
                    "order": 0
                },
                {
                    "adult": false,
                    "gender": 1,
                    "id": 66959,
                    "known_for_department": "Acting",
                    "name": "Verónica Llinás",
                    "original_name": "Verónica Llinás",
                    "popularity": 0.4266,
                    "profile_path": "/eRT77QU9BxH6l1snTSGwYqPR8AC.jpg",
                    "cast_id": 17,
                    "character": "Self (voice)",
                    "credit_id": "5e9efadceec5b5001c41bba5",
                    "order": 1
                },
                {
                    "adult": false,
                    "gender": 0,
                    "id": 1957315,
                    "known_for_department": "Acting",
                    "name": "Daniel Natanson",
                    "original_name": "Daniel Natanson",
                    "popularity": 0.0214,
                    "profile_path": null,
                    "cast_id": 18,
                    "character": "Self (voice)",
                    "credit_id": "5e9efaf22790bf001f07e440",
                    "order": 2
                },
                {
                    "adult": false,
                    "gender": 0,
                    "id": 2128004,
                    "known_for_department": "Writing",
                    "name": "Mario Mactas",
                    "original_name": "Mario Mactas",
                    "popularity": 0.0357,
                    "profile_path": null,
                    "cast_id": 19,
                    "character": "Self (voice)",
                    "credit_id": "5e9efb0a1f3319001d4c6772",
                    "order": 3
                },
                {
                    "adult": false,
                    "gender": 0,
                    "id": 2609916,
                    "known_for_department": "Acting",
                    "name": "Eduardo Gamba",
                    "original_name": "Eduardo Gamba",
                    "popularity": 0.052,
                    "profile_path": null,
                    "cast_id": 22,
                    "character": "Mr. G.",
                    "credit_id": "5e9efe8524f2ce001f30b0d8",
                    "order": 4
                },
                {
                    "adult": false,
                    "gender": 0,
                    "id": 555975,
                    "known_for_department": "Editing",
                    "name": "Nicolás Goldbart",
                    "original_name": "Nicolás Goldbart",
                    "popularity": 0.0777,
                    "profile_path": "/zl5DeFJlclwMkpShPlp7SmuOv3D.jpg",
                    "cast_id": 23,
                    "character": "Young G.",
                    "credit_id": "5e9efea0e63571001df905dc",
                    "order": 5
                },
                {
                    "adult": false,
                    "gender": 2,
                    "id": 935388,
                    "known_for_department": "Directing",
                    "name": "Rafael Filippelli",
                    "original_name": "Rafael Filippelli",
                    "popularity": 0.0637,
                    "profile_path": "/7Y9EA5Dc9Z7VAaJcEaZ2hbIx1f5.jpg",
                    "cast_id": 24,
                    "character": "Lawyer",
                    "credit_id": "5e9efee22790bf001f07eaf1",
                    "order": 6
                },
                {
                    "adult": false,
                    "gender": 2,
                    "id": 2439028,
                    "known_for_department": "Directing",
                    "name": "Ulises de la Orden",
                    "original_name": "Ulises de la Orden",
                    "popularity": 0.1225,
                    "profile_path": "/yHKEVRyv1I4WRooxTm37lNGsod2.jpg",
                    "cast_id": 25,
                    "character": "Uruguayan",
                    "credit_id": "5e9effc01f331900244c6e38",
                    "order": 7
                },
                {
                    "adult": false,
                    "gender": 0,
                    "id": 1817493,
                    "known_for_department": "Art",
                    "name": "Astrid Lund Petersen",
                    "original_name": "Astrid Lund Petersen",
                    "popularity": 0.0286,
                    "profile_path": null,
                    "cast_id": 26,
                    "character": "Singer",
                    "credit_id": "5e9effea0f3655002375b314",
                    "order": 8
                },
                {
                    "adult": false,
                    "gender": 0,
                    "id": 2609921,
                    "known_for_department": "Acting",
                    "name": "Sergio Saad",
                    "original_name": "Sergio Saad",
                    "popularity": 0.0071,
                    "profile_path": null,
                    "cast_id": 27,
                    "character": "Sailor",
                    "credit_id": "5e9f003f0f3655001c75bf80",
                    "order": 9
                },
                {
                    "adult": false,
                    "gender": 0,
                    "id": 2609926,
                    "known_for_department": "Acting",
                    "name": "Eduardo 'Fatiga' Serrano",
                    "original_name": "Eduardo 'Fatiga' Serrano",
                    "popularity": 0.0071,
                    "profile_path": null,
                    "cast_id": 28,
                    "character": "Lifeguard",
                    "credit_id": "5e9f00e2d05a03001cbe6d17",
                    "order": 10
                },
                {
                    "adult": false,
                    "gender": 0,
                    "id": 2276357,
                    "known_for_department": "Editing",
                    "name": "Wenceslao Bonelli",
                    "original_name": "Wenceslao Bonelli",
                    "popularity": 0.0071,
                    "profile_path": null,
                    "cast_id": 29,
                    "character": "Champion",
                    "credit_id": "5e9f00fad05a030020be6e84",
                    "order": 11
                },
                {
                    "adult": false,
                    "gender": 0,
                    "id": 2609930,
                    "known_for_department": "Acting",
                    "name": "Luis Pierucci",
                    "original_name": "Luis Pierucci",
                    "popularity": 0.0663,
                    "profile_path": null,
                    "cast_id": 30,
                    "character": "Guide",
                    "credit_id": "5e9f016ce635710024f91299",
                    "order": 12
                },
                {
                    "adult": false,
                    "gender": 0,
                    "id": 2609931,
                    "known_for_department": "Acting",
                    "name": "Ricardo Mannero",
                    "original_name": "Ricardo Mannero",
                    "popularity": 0.0071,
                    "profile_path": null,
                    "cast_id": 31,
                    "character": "Aquanaut",
                    "credit_id": "5e9f019f24f2ce002230b731",
                    "order": 13
                },
                {
                    "adult": false,
                    "gender": 0,
                    "id": 2609932,
                    "known_for_department": "Acting",
                    "name": "Liliana Cuomo",
                    "original_name": "Liliana Cuomo",
                    "popularity": 0.0409,
                    "profile_path": null,
                    "cast_id": 32,
                    "character": "Mermaid",
                    "credit_id": "5e9f0267eec5b5002141b744",
                    "order": 14
                },
                {
                    "adult": false,
                    "gender": 0,
                    "id": 2609935,
                    "known_for_department": "Acting",
                    "name": "Roberto Edgar Ojeda",
                    "original_name": "Roberto Edgar Ojeda",
                    "popularity": 0,
                    "profile_path": null,
                    "cast_id": 35,
                    "character": "Guitarist #1",
                    "credit_id": "5e9f02ce24f2ce001f30b38f",
                    "order": 15
                },
                {
                    "adult": false,
                    "gender": 0,
                    "id": 2609936,
                    "known_for_department": "Acting",
                    "name": "Osvaldo Lucero",
                    "original_name": "Osvaldo Lucero",
                    "popularity": 0.0418,
                    "profile_path": null,
                    "cast_id": 36,
                    "character": "Guitarist #2",
                    "credit_id": "5e9f02e5eec5b5002141b815",
                    "order": 16
                },
                {
                    "adult": false,
                    "gender": 0,
                    "id": 2609938,
                    "known_for_department": "Acting",
                    "name": "Eugenia Varas",
                    "original_name": "Eugenia Varas",
                    "popularity": 0.0071,
                    "profile_path": null,
                    "cast_id": 37,
                    "character": "Swimmer",
                    "credit_id": "5e9f0332d05a03001cbe6edd",
                    "order": 17
                },
                {
                    "adult": false,
                    "gender": 2,
                    "id": 1293509,
                    "known_for_department": "Directing",
                    "name": "Mariano Llinás",
                    "original_name": "Mariano Llinás",
                    "popularity": 0.3694,
                    "profile_path": "/dfCOcnGqMXzr8BdaHHQ9ohdGfvN.jpg",
                    "cast_id": 38,
                    "character": "Model",
                    "credit_id": "607c4ece9f37b00029af02cb",
                    "order": 18
                },
                {
                    "adult": false,
                    "gender": 2,
                    "id": 2609907,
                    "known_for_department": "Acting",
                    "name": "Alejandro Zucco",
                    "original_name": "Alejandro Zucco",
                    "popularity": 0,
                    "profile_path": null,
                    "cast_id": 40,
                    "character": "Son",
                    "credit_id": "673a212e443543191ccbf279",
                    "order": 19
                },
                {
                    "adult": false,
                    "gender": 0,
                    "id": 1331816,
                    "known_for_department": "Acting",
                    "name": "Liliana Cuomo",
                    "original_name": "Liliana Cuomo",
                    "popularity": 0.0429,
                    "profile_path": "/4UXHgzfv9bxSddf2b19bByqEpAK.jpg",
                    "cast_id": 41,
                    "character": "Mermaid",
                    "credit_id": "676cb5ad0c4402b631927590",
                    "order": 20
                },
                {
                    "adult": false,
                    "gender": 2,
                    "id": 2609934,
                    "known_for_department": "Acting",
                    "name": "Francisco Miguel Fernández",
                    "original_name": "Francisco Miguel Fernández",
                    "popularity": 0.0071,
                    "profile_path": null,
                    "cast_id": 42,
                    "character": "Singer",
                    "credit_id": "67dfff83ce605a1ed1c71b63",
                    "order": 21
                }
            ],
            "crew": [
                {
                    "adult": false,
                    "gender": 2,
                    "id": 1293509,
                    "known_for_department": "Directing",
                    "name": "Mariano Llinás",
                    "original_name": "Mariano Llinás",
                    "popularity": 0.3694,
                    "profile_path": "/dfCOcnGqMXzr8BdaHHQ9ohdGfvN.jpg",
                    "credit_id": "53019a8d92514121951ba206",
                    "department": "Directing",
                    "job": "Director"
                },
                {
                    "adult": false,
                    "gender": 0,
                    "id": 1791449,
                    "known_for_department": "Editing",
                    "name": "Agustín Rolandelli",
                    "original_name": "Agustín Rolandelli",
                    "popularity": 0.0281,
                    "profile_path": null,
                    "credit_id": "5b07d0e7925141725f00425a",
                    "department": "Editing",
                    "job": "Editor"
                },
                {
                    "adult": false,
                    "gender": 0,
                    "id": 555975,
                    "known_for_department": "Editing",
                    "name": "Nicolás Goldbart",
                    "original_name": "Nicolás Goldbart",
                    "popularity": 0.0777,
                    "profile_path": "/zl5DeFJlclwMkpShPlp7SmuOv3D.jpg",
                    "credit_id": "5b07d0fc925141721200342d",
                    "department": "Editing",
                    "job": "Editor"
                },
                {
                    "adult": false,
                    "gender": 2,
                    "id": 68145,
                    "known_for_department": "Camera",
                    "name": "Lucio Bonelli",
                    "original_name": "Lucio Bonelli",
                    "popularity": 0.1437,
                    "profile_path": "/cZZN1Tz20pS3C3TfVi4ErLDYYyu.jpg",
                    "credit_id": "5b07d1150e0a267b5d003bdd",
                    "department": "Camera",
                    "job": "Director of Photography"
                },
                {
                    "adult": false,
                    "gender": 2,
                    "id": 1293509,
                    "known_for_department": "Directing",
                    "name": "Mariano Llinás",
                    "original_name": "Mariano Llinás",
                    "popularity": 0.3694,
                    "profile_path": "/dfCOcnGqMXzr8BdaHHQ9ohdGfvN.jpg",
                    "credit_id": "5b07d13c0e0a267b5d003bfb",
                    "department": "Writing",
                    "job": "Writer"
                },
                {
                    "adult": false,
                    "gender": 2,
                    "id": 1509683,
                    "known_for_department": "Production",
                    "name": "Alejandro Israel",
                    "original_name": "Alejandro Israel",
                    "popularity": 0.0512,
                    "profile_path": "/8bk9ZTFdXCDG6EBP7S5YEsFnHHX.jpg",
                    "credit_id": "64cd4e7a8289a001250e648c",
                    "department": "Production",
                    "job": "Production Manager"
                },
                {
                    "adult": false,
                    "gender": 2,
                    "id": 1587464,
                    "known_for_department": "Sound",
                    "name": "Gabriel Chwojnik",
                    "original_name": "Gabriel Chwojnik",
                    "popularity": 0.0429,
                    "profile_path": "/qr3H8IHD78zjroizTiveDc9w7hT.jpg",
                    "credit_id": "5e9ef5d92790bf001d07df9c",
                    "department": "Sound",
                    "job": "Original Music Composer"
                },
                {
                    "adult": false,
                    "gender": 0,
                    "id": 2609902,
                    "known_for_department": "Production",
                    "name": "Manuela Willimburgh",
                    "original_name": "Manuela Willimburgh",
                    "popularity": 0.0322,
                    "profile_path": null,
                    "credit_id": "5e9ef869eec5b5002141a836",
                    "department": "Production",
                    "job": "Executive Producer"
                },
                {
                    "adult": false,
                    "gender": 2,
                    "id": 1509683,
                    "known_for_department": "Production",
                    "name": "Alejandro Israel",
                    "original_name": "Alejandro Israel",
                    "popularity": 0.0512,
                    "profile_path": "/8bk9ZTFdXCDG6EBP7S5YEsFnHHX.jpg",
                    "credit_id": "5e9ef8ae24f2ce002230a937",
                    "department": "Production",
                    "job": "Production Director"
                },
                {
                    "adult": false,
                    "gender": 2,
                    "id": 1618439,
                    "known_for_department": "Sound",
                    "name": "Federico Esquerro",
                    "original_name": "Federico Esquerro",
                    "popularity": 0.0311,
                    "profile_path": null,
                    "credit_id": "5e9ef909eec5b5001c41ba72",
                    "department": "Sound",
                    "job": "Sound"
                },
                {
                    "adult": false,
                    "gender": 0,
                    "id": 2062853,
                    "known_for_department": "Sound",
                    "name": "Fernando Ribero",
                    "original_name": "Fernando Ribero",
                    "popularity": 0.0975,
                    "profile_path": null,
                    "credit_id": "5e9ef91d0ed2ab0026e6f3ae",
                    "department": "Sound",
                    "job": "Sound Recordist"
                },
                {
                    "adult": false,
                    "gender": 2,
                    "id": 2307443,
                    "known_for_department": "Sound",
                    "name": "Rufino Basavilbaso",
                    "original_name": "Rufino Basavilbaso",
                    "popularity": 0.0286,
                    "profile_path": null,
                    "credit_id": "5e9ef94cd05a03001cbe64be",
                    "department": "Sound",
                    "job": "Sound Recordist"
                },
                {
                    "adult": false,
                    "gender": 0,
                    "id": 2062851,
                    "known_for_department": "Sound",
                    "name": "Ana Mouriño",
                    "original_name": "Ana Mouriño",
                    "popularity": 0.0239,
                    "profile_path": null,
                    "credit_id": "5e9ef9800f3655001c75aff1",
                    "department": "Sound",
                    "job": "Sound Recordist"
                },
                {
                    "adult": false,
                    "gender": 2,
                    "id": 1467069,
                    "known_for_department": "Sound",
                    "name": "Guillermo Picco",
                    "original_name": "Guillermo Picco",
                    "popularity": 0.0143,
                    "profile_path": null,
                    "credit_id": "5e9ef99524f2ce002230aa27",
                    "department": "Sound",
                    "job": "Sound Recordist"
                },
                {
                    "adult": false,
                    "gender": 2,
                    "id": 1817498,
                    "known_for_department": "Camera",
                    "name": "Martín Mohadeb",
                    "original_name": "Martín Mohadeb",
                    "popularity": 0.0708,
                    "profile_path": null,
                    "credit_id": "5e9ef9f324f2ce002230aa51",
                    "department": "Camera",
                    "job": "Additional Director of Photography"
                },
                {
                    "adult": false,
                    "gender": 0,
                    "id": 2609905,
                    "known_for_department": "Art",
                    "name": "Juan Pablo Cambariere",
                    "original_name": "Juan Pablo Cambariere",
                    "popularity": 0,
                    "profile_path": null,
                    "credit_id": "5e9efa0f2790bf002507dd66",
                    "department": "Art",
                    "job": "Graphic Designer"
                },
                {
                    "adult": false,
                    "gender": 2,
                    "id": 2609907,
                    "known_for_department": "Acting",
                    "name": "Alejandro Zucco",
                    "original_name": "Alejandro Zucco",
                    "popularity": 0,
                    "profile_path": null,
                    "credit_id": "5e9efb2ed05a03001cbe658b",
                    "department": "Production",
                    "job": "Production Coordinator"
                },
                {
                    "adult": false,
                    "gender": 2,
                    "id": 1706305,
                    "known_for_department": "Acting",
                    "name": "Agustín Mendilaharzu",
                    "original_name": "Agustín Mendilaharzu",
                    "popularity": 0.0739,
                    "profile_path": "/8lUXtYiw27b2WU3rzbd8sY2qv7x.jpg",
                    "credit_id": "5e9efb4be63571001ff90cbd",
                    "department": "Production",
                    "job": "Researcher"
                }
            ]
        },
        "videos": {
            "results": []
        },
        "images": {
            "backdrops": [],
            "logos": [],
            "posters": [
                {
                    "aspect_ratio": 0.667,
                    "height": 900,
                    "iso_3166_1": "ES",
                    "iso_639_1": "es",
                    "file_path": "/jqHoLGPaYJou37YZXy0CytikU2i.jpg",
                    "vote_average": 1.016,
                    "vote_count": 11,
                    "width": 600
                },
                {
                    "aspect_ratio": 0.667,
                    "height": 1500,
                    "iso_3166_1": "ES",
                    "iso_639_1": "es",
                    "file_path": "/fPRv17s4Rdp6zyqfRNFl26qmztf.jpg",
                    "vote_average": 8.034,
                    "vote_count": 10,
                    "width": 1000
                },
                {
                    "aspect_ratio": 0.705,
                    "height": 752,
                    "iso_3166_1": "ES",
                    "iso_639_1": "es",
                    "file_path": "/dgQYF4K2porH4cMvUDNKb8zWMQt.jpg",
                    "vote_average": 1.75,
                    "vote_count": 2,
                    "width": 530
                }
            ]
        }
    }
}